{
    "data": [
        0.21777163904235727,
        0.21602631185528479,
        0.19368090827606813,
        0.2112345804873076,
        0.2019761697181052,
        0.2290877525252525,
        0.22525730833952962,
        0.22863197551212622,
        0.21368071191165433,
        0.21055053788183858,
        0.23212559012570388,
        0.26442085832948775,
        0.2880284926470588,
        0.3044074772766249,
        0.32784493538974574,
        0.35039643900403394,
        0.47173327811141025
    ],
    "knowledges": {
        "r8S3g": {
            "data": [
                0.18636363636363637,
                0.18386346004654772,
                0.16510161177295024,
                0.1761540640045313,
                0.1850851438637698,
                0.20535714285714285,
                0.18786738772631084,
                0.21929298981426004,
                0.177319587628866,
                0.17049576783555018,
                0.21557719054242003,
                0.2176991150442478,
                0.24563953488372092,
                0.21415607985480944,
                0.37142857142857144,
                0.4791666666666667,
                0.4112903225806452
            ],
            "sub_knowledges": {
                "r8S3g_l0p5viby": {
                    "data": [
                        0.18862042088854247,
                        0.18016272762495156,
                        0.16181102362204725,
                        0.16925351071692535,
                        0.1783273673934266,
                        0.1819526627218935,
                        0.18228782287822878,
                        0.2109375,
                        0.15142857142857144,
                        0.1618705035971223,
                        0.2484472049689441,
                        0.2356020942408377,
                        0.21739130434782608,
                        0.18518518518518517,
                        0.3673469387755102,
                        0.42857142857142855,
                        0.3958333333333333
                    ],
                    "participants": [
                        1283,
                        2581,
                        2540,
                        1353,
                        3073,
                        2028,
                        1355,
                        512,
                        350,
                        278,
                        161,
                        191,
                        276,
                        162,
                        49,
                        14,
                        48
                    ]
                },
                "r8S3g_n0m9rsw4": {
                    "data": [
                        0.18475236505286588,
                        0.18633540372670807,
                        0.16692056583242654,
                        0.18044077134986225,
                        0.18890113928702681,
                        0.21750255885363357,
                        0.19047619047619047,
                        0.222990492653414,
                        0.19193548387096773,
                        0.17486338797814208,
                        0.2060931899641577,
                        0.20855614973262032,
                        0.2645631067961165,
                        0.2262210796915167,
                        0.373015873015873,
                        0.5,
                        0.42105263157894735
                    ],
                    "participants": [
                        1797,
                        3864,
                        4595,
                        2178,
                        5442,
                        3908,
                        2898,
                        1157,
                        620,
                        549,
                        558,
                        374,
                        412,
                        389,
                        126,
                        34,
                        76
                    ]
                }
            }
        },
        "t5V9e": {
            "data": [
                0.25675675675675674,
                0.26436781609195403,
                0.17893624515674533,
                0.1848362494392104,
                0.17672648178357803,
                0.21059701492537314,
                0.1884297520661157,
                0.21816930488644184,
                0.21922110552763818,
                0.215311004784689,
                0.28872497365648053,
                0.25675675675675674,
                0.328335832083958,
                0.27555555555555555,
                0.36027713625866054,
                0.30368098159509205,
                0.44375
            ],
            "sub_knowledges": {
                "t5V9e_e1k6cixp": {
                    "data": [
                        0.25675675675675674,
                        0.26436781609195403,
                        0.17893624515674533,
                        0.1848362494392104,
                        0.17672648178357803,
                        0.21059701492537314,
                        0.1884297520661157,
                        0.21816930488644184,
                        0.21922110552763818,
                        0.215311004784689,
                        0.28872497365648053,
                        0.25675675675675674,
                        0.328335832083958,
                        0.27555555555555555,
                        0.36027713625866054,
                        0.30368098159509205,
                        0.44375
                    ],
                    "participants": [
                        518,
                        2262,
                        2839,
                        2229,
                        5517,
                        6700,
                        6050,
                        2906,
                        1592,
                        1254,
                        949,
                        888,
                        667,
                        450,
                        433,
                        326,
                        160
                    ]
                }
            }
        },
        "m3D1v": {
            "data": [
                0.30844793713163066,
                0.2769104354971241,
                0.31097560975609756,
                0.28173374613003094,
                0.26430885529157666,
                0.2744332682780363,
                0.2667068757539204,
                0.25788410750349544,
                0.2363076923076923,
                0.23285899094437257,
                0.2638788752703677,
                0.2590471827759963,
                0.30694354315379624,
                0.3198992443324937,
                0.4036624203821656,
                0.39471106758080315,
                0.4390495867768595
            ],
            "sub_knowledges": {
                "m3D1v_r1d7fr3l": {
                    "data": [
                        0.3193717277486911,
                        0.27888655462184875,
                        0.30295566502463056,
                        0.26068883610451304,
                        0.2535584243627938,
                        0.2534808996786862,
                        0.24263038548752835,
                        0.24812186978297163,
                        0.20851632614092036,
                        0.22634462151394422,
                        0.2451938228805547,
                        0.24038735403019082,
                        0.2806528662420382,
                        0.32403297400126824,
                        0.39938712972420837,
                        0.37992831541218636,
                        0.4194407456724368
                    ],
                    "participants": [
                        382,
                        1904,
                        1218,
                        1684,
                        3021,
                        5602,
                        6615,
                        4792,
                        5237,
                        4016,
                        3173,
                        3511,
                        2512,
                        1577,
                        979,
                        837,
                        751
                    ]
                },
                "m3D1v_v3d9is1x": {
                    "data": [
                        0.3235294117647059,
                        0.4351464435146444,
                        0.41843971631205673,
                        0.43125,
                        0.3403361344537815,
                        0.43263473053892215,
                        0.3996003996003996,
                        0.34889148191365227,
                        0.4482225656877898,
                        0.29766803840877915,
                        0.3752620545073375,
                        0.3514644351464435,
                        0.41830065359477125,
                        0.29343629343629346,
                        0.44696969696969696,
                        0.4,
                        0.5196850393700787
                    ],
                    "participants": [
                        68,
                        239,
                        141,
                        160,
                        476,
                        668,
                        1001,
                        857,
                        647,
                        729,
                        477,
                        478,
                        306,
                        259,
                        132,
                        125,
                        127
                    ]
                },
                "m3D1v_t0v5ts9h": {
                    "data": [
                        0.22033898305084745,
                        0.13402061855670103,
                        0.26495726495726496,
                        0.40425531914893614,
                        0.2463768115942029,
                        0.30434782608695654,
                        0.3056379821958457,
                        0.2182741116751269,
                        0.25,
                        0.2012012012012012,
                        0.2759295499021526,
                        0.3156498673740053,
                        0.42803030303030304,
                        0.3221476510067114,
                        0.3931034482758621,
                        0.5932203389830508,
                        0.4888888888888889
                    ],
                    "participants": [
                        59,
                        291,
                        117,
                        94,
                        207,
                        391,
                        674,
                        788,
                        616,
                        666,
                        511,
                        377,
                        264,
                        149,
                        145,
                        59,
                        90
                    ]
                }
            }
        },
        "y9W5d": {
            "data": [
                0.4224137931034483,
                0.22743682310469315,
                0.27582846003898637,
                0.2857142857142857,
                0.23271889400921658,
                0.22736897829539437,
                0.24158653846153846,
                0.2257699915230291,
                0.2115219260533104,
                0.20666352349520667,
                0.23288039822413562,
                0.2914012738853503,
                0.31469194312796206,
                0.3352880303552949,
                0.33064190553088413,
                0.39755973563802743,
                0.5226710634789777
            ],
            "sub_knowledges": {
                "y9W5d_c0w4mj5h": {
                    "data": [
                        0.4823529411764706,
                        0.250936329588015,
                        0.2792452830188679,
                        0.29292929292929293,
                        0.23582089552238805,
                        0.22596153846153846,
                        0.2391160949868074,
                        0.22606568832983928,
                        0.20700773860705074,
                        0.2120246864423651,
                        0.2329996548153262,
                        0.2916984006092917,
                        0.3052570432762126,
                        0.34777651083238315,
                        0.3284864507600793,
                        0.3533434650455927,
                        0.47607655502392343
                    ],
                    "participants": [
                        85,
                        801,
                        795,
                        693,
                        1340,
                        3120,
                        3032,
                        2862,
                        4652,
                        5023,
                        5794,
                        5252,
                        3443,
                        1754,
                        1513,
                        1316,
                        836
                    ]
                },
                "y9W5d_p8g6dgtv": {
                    "data": [
                        0.38095238095238093,
                        0.18461538461538463,
                        0.358695652173913,
                        0.24561403508771928,
                        0.2289156626506024,
                        0.30727762803234504,
                        0.25584795321637427,
                        0.2770083102493075,
                        0.21805392731535755,
                        0.189718482252142,
                        0.24233128834355827,
                        0.32642487046632124,
                        0.3548951048951049,
                        0.41155234657039713,
                        0.3344316309719934,
                        0.5112359550561798,
                        0.6
                    ],
                    "participants": [
                        21,
                        130,
                        92,
                        171,
                        249,
                        371,
                        684,
                        361,
                        853,
                        817,
                        978,
                        1351,
                        1144,
                        554,
                        607,
                        356,
                        240
                    ]
                },
                "y9W5d_e2j7p95s": {
                    "data": [
                        0.0,
                        0.15254237288135594,
                        0.2014388489208633,
                        0.32075471698113206,
                        0.2108843537414966,
                        0.13937282229965156,
                        0.23648648648648649,
                        0.16455696202531644,
                        0.26129032258064516,
                        0.18164435946462715,
                        0.2178517397881997,
                        0.2390139335476956,
                        0.29505813953488375,
                        0.22673434856175972,
                        0.3333333333333333,
                        0.4576271186440678,
                        0.6715328467153284
                    ],
                    "participants": [
                        10,
                        177,
                        139,
                        53,
                        147,
                        287,
                        444,
                        316,
                        310,
                        523,
                        661,
                        933,
                        688,
                        591,
                        357,
                        295,
                        137
                    ]
                }
            }
        },
        "k4W1c": {
            "data": [
                1.0,
                0.3114754098360656,
                0.3333333333333333,
                0.2831858407079646,
                0.17575757575757575,
                0.25443786982248523,
                0.28185328185328185,
                0.22562674094707522,
                0.1825503355704698,
                0.237017310252996,
                0.21052631578947367,
                0.34142640364188165,
                0.24334600760456274,
                0.4727272727272727,
                0.36507936507936506,
                0.4506172839506173,
                0.4596774193548387
            ],
            "sub_knowledges": {
                "k4W1c_h5r6nux7": {
                    "data": [
                        1.0,
                        0.3114754098360656,
                        0.3333333333333333,
                        0.2831858407079646,
                        0.17575757575757575,
                        0.25443786982248523,
                        0.28185328185328185,
                        0.22562674094707522,
                        0.1825503355704698,
                        0.237017310252996,
                        0.21052631578947367,
                        0.34142640364188165,
                        0.24334600760456274,
                        0.4727272727272727,
                        0.36507936507936506,
                        0.4506172839506173,
                        0.4596774193548387
                    ],
                    "participants": [
                        6,
                        61,
                        69,
                        113,
                        165,
                        338,
                        259,
                        359,
                        745,
                        751,
                        950,
                        659,
                        526,
                        165,
                        189,
                        162,
                        124
                    ]
                }
            }
        },
        "s8Y2f": {
            "data": [
                0.8333333333333334,
                0.25,
                0.42857142857142855,
                0.175,
                0.3013698630136986,
                0.14171656686626746,
                0.30685920577617326,
                0.19047619047619047,
                0.23094688221709006,
                0.2018018018018018,
                0.20820668693009117,
                0.24330900243309003,
                0.2740963855421687,
                0.2891891891891892,
                0.3025830258302583,
                0.4,
                0.4198473282442748
            ],
            "sub_knowledges": {
                "s8Y2f_v4x8by9j": {
                    "data": [
                        0.8333333333333334,
                        0.25,
                        0.42857142857142855,
                        0.175,
                        0.3013698630136986,
                        0.14171656686626746,
                        0.30685920577617326,
                        0.19047619047619047,
                        0.23094688221709006,
                        0.2018018018018018,
                        0.20820668693009117,
                        0.24330900243309003,
                        0.2740963855421687,
                        0.2891891891891892,
                        0.3025830258302583,
                        0.4,
                        0.4198473282442748
                    ],
                    "participants": [
                        6,
                        68,
                        63,
                        120,
                        146,
                        501,
                        277,
                        231,
                        433,
                        555,
                        658,
                        822,
                        664,
                        370,
                        271,
                        205,
                        131
                    ]
                }
            }
        },
        "g7R2j": {
            "data": [
                0.1797752808988764,
                0.15371024734982333,
                0.15066225165562913,
                0.15151515151515152,
                0.17184643510054845,
                0.2197483059051307,
                0.17309941520467836,
                0.16021671826625386,
                0.14801864801864803,
                0.16984615384615384,
                0.16032608695652173,
                0.19937606352807713,
                0.2362817362817363,
                0.2456445993031359,
                0.2735648476257973,
                0.28191000918273645,
                0.43579454253611555
            ],
            "sub_knowledges": {
                "g7R2j_e0v1yls8": {
                    "data": [
                        0.29411764705882354,
                        0.15723270440251572,
                        0.1422924901185771,
                        0.15689381933438987,
                        0.19012345679012346,
                        0.22234392113910187,
                        0.1744266851980542,
                        0.157502329916123,
                        0.14518413597733712,
                        0.16483516483516483,
                        0.17117726657645466,
                        0.1961335676625659,
                        0.24031007751937986,
                        0.23918396060499472,
                        0.2680320569902048,
                        0.2719546742209632,
                        0.463882618510158
                    ],
                    "participants": [
                        51,
                        477,
                        506,
                        631,
                        405,
                        913,
                        1439,
                        1073,
                        1412,
                        1365,
                        1478,
                        2845,
                        3999,
                        2843,
                        2246,
                        1765,
                        886
                    ]
                },
                "g7R2j_j1g8gd3v": {
                    "data": [
                        0.02631578947368421,
                        0.1348314606741573,
                        0.19387755102040816,
                        0.13043478260869565,
                        0.11971830985915492,
                        0.2,
                        0.16605166051660517,
                        0.1735159817351598,
                        0.1611842105263158,
                        0.19615384615384615,
                        0.11602209944751381,
                        0.21292217327459617,
                        0.21807909604519773,
                        0.2762063227953411,
                        0.2951388888888889,
                        0.324455205811138,
                        0.36666666666666664
                    ],
                    "participants": [
                        38,
                        89,
                        98,
                        161,
                        142,
                        120,
                        271,
                        219,
                        304,
                        260,
                        362,
                        681,
                        885,
                        601,
                        576,
                        413,
                        360
                    ]
                }
            }
        },
        "b3C9s": {
            "data": [
                0.3,
                0.1336405529953917,
                0.13636363636363635,
                0.33727810650887574,
                0.21835443037974683,
                0.26448362720403024,
                0.26534296028880866,
                0.16756756756756758,
                0.23669309173272934,
                0.18090452261306533,
                0.21928817451205512,
                0.30762489044697633,
                0.34278668310727495,
                0.37263626251390436,
                0.3426254434870755,
                0.3455538221528861,
                0.5121668597914253
            ],
            "sub_knowledges": {
                "b3C9s_l4z6od7y": {
                    "data": [
                        1.0,
                        0.2111801242236025,
                        0.11464968152866242,
                        0.32653061224489793,
                        0.4036697247706422,
                        0.29770992366412213,
                        0.32,
                        0.1978798586572438,
                        0.2986425339366516,
                        0.19656019656019655,
                        0.23076923076923078,
                        0.3689922480620155,
                        0.369215291750503,
                        0.3859030837004405,
                        0.38762511373976344,
                        0.39748953974895396,
                        0.5625
                    ],
                    "participants": [
                        6,
                        161,
                        157,
                        98,
                        109,
                        262,
                        275,
                        283,
                        442,
                        407,
                        468,
                        645,
                        994,
                        1135,
                        1099,
                        717,
                        496
                    ]
                },
                "b3C9s_j0v1yls8": {
                    "data": [
                        0.0,
                        0.08791208791208792,
                        0.3157894736842105,
                        0.352112676056338,
                        0.12077294685990338,
                        0.2,
                        0.2114695340501792,
                        0.13602941176470587,
                        0.1746031746031746,
                        0.14736842105263157,
                        0.20595533498759305,
                        0.22782258064516128,
                        0.30095541401273884,
                        0.34992458521870284,
                        0.28604118993135014,
                        0.27964601769911507,
                        0.444141689373297
                    ],
                    "participants": [
                        14,
                        273,
                        19,
                        71,
                        207,
                        135,
                        279,
                        272,
                        441,
                        190,
                        403,
                        496,
                        628,
                        663,
                        874,
                        565,
                        367
                    ]
                }
            }
        }
    }
}